sleep_detector/__init__.py
sleep_detector/cli.py
sleep_detector/config.py
sleep_detector/core.py
sleep_detector-0.1.0.dist-info/licenses/LICENSE
sleep_detector-0.1.0.dist-info/METADATA
sleep_detector-0.1.0.dist-info/WHEEL
sleep_detector-0.1.0.dist-info/entry_points.txt
sleep_detector-0.1.0.dist-info/top_level.txt
sleep_detector-0.1.0.dist-info/RECORD
