Metadata-Version: 2.4
Name: sleep-detector
Version: 0.1.0
Summary: Detects sleep() calls in your codebase
Author: Mor Dabastany
Author-email: morpci@gmail.com
Requires-Python: >=3.7
License-File: LICENSE
Requires-Dist: toml
Dynamic: author
Dynamic: author-email
Dynamic: license-file
Dynamic: requires-dist
Dynamic: requires-python
Dynamic: summary
